## Hello world

1. Create a new file called `HelloWorld.java` with the following content:
```java
public class HelloWorld {
	public static void main(String[] args) { 
		System.out.println("Hello World"); 
	} 
}
```

2. **Compile the Java program**: Compile the `HelloWorld.java` file using the `javac` command:
```
javac HelloWorld.java
```
The result will be a new `HelloWorld.class` file located within your current working directory.

3. **Run the Java program**: Execute the compiled Java program using the `java` command:
```
java HelloWorld
```

4. To view the resultant bytecode, run `javap` with the `-c` option to disassemble the bytecode:
```
javap -c HelloWorld
```

```java
Compiled from "HelloWorld.java"
public class HelloWorld {
  public HelloWorld();
    Code:
       0: aload_0
       1: invokespecial #1                  // Method java/lang/Object."<init>":()V
       4: return

  public static void main(java.lang.String[]);
    Code:
       0: getstatic     #7                  // Field java/lang/System.out:Ljava/io/PrintStream;
       3: ldc           #13                 // String Hello World!
       5: invokevirtual #15                 // Method java/io/PrintStream.println:(Ljava/lang/String;)V
       8: return
}
```

If you want a more detailed view, you can use the `-v` option:
```
javap -v HelloWorld
```

```java
Classfile /home/vinico/dev/temp/jhello/HelloWorld.class
  Last modified Sep 15, 2023; size 426 bytes
  SHA-256 checksum af4b1fb61941e648b10d8994eaa32c19d6fcb4be0b6a60233d45db5a2b2ab924
  Compiled from "HelloWorld.java"
public class HelloWorld
  minor version: 0
  major version: 65
  flags: (0x0021) ACC_PUBLIC, ACC_SUPER
  this_class: #21                         // HelloWorld
  super_class: #2                         // java/lang/Object
  interfaces: 0, fields: 0, methods: 2, attributes: 1
Constant pool:
   #1 = Methodref          #2.#3          // java/lang/Object."<init>":()V
   #2 = Class              #4             // java/lang/Object
   #3 = NameAndType        #5:#6          // "<init>":()V
   #4 = Utf8               java/lang/Object
   #5 = Utf8               <init>
   #6 = Utf8               ()V
   #7 = Fieldref           #8.#9          // java/lang/System.out:Ljava/io/PrintStream;
   #8 = Class              #10            // java/lang/System
   #9 = NameAndType        #11:#12        // out:Ljava/io/PrintStream;
  #10 = Utf8               java/lang/System
  #11 = Utf8               out
  #12 = Utf8               Ljava/io/PrintStream;
  #13 = String             #14            // Hello World!
  #14 = Utf8               Hello World!
  #15 = Methodref          #16.#17        // java/io/PrintStream.println:(Ljava/lang/String;)V
  #16 = Class              #18            // java/io/PrintStream
  #17 = NameAndType        #19:#20        // println:(Ljava/lang/String;)V
  #18 = Utf8               java/io/PrintStream
  #19 = Utf8               println
  #20 = Utf8               (Ljava/lang/String;)V
  #21 = Class              #22            // HelloWorld
  #22 = Utf8               HelloWorld
  #23 = Utf8               Code
  #24 = Utf8               LineNumberTable
  #25 = Utf8               main
  #26 = Utf8               ([Ljava/lang/String;)V
  #27 = Utf8               SourceFile
  #28 = Utf8               HelloWorld.java
{
  public HelloWorld();
    descriptor: ()V
    flags: (0x0001) ACC_PUBLIC
    Code:
      stack=1, locals=1, args_size=1
         0: aload_0
         1: invokespecial #1                  // Method java/lang/Object."<init>":()V
         4: return
      LineNumberTable:
        line 1: 0

  public static void main(java.lang.String[]);
    descriptor: ([Ljava/lang/String;)V
    flags: (0x0009) ACC_PUBLIC, ACC_STATIC
    Code:
      stack=2, locals=1, args_size=1
         0: getstatic     #7                  // Field java/lang/System.out:Ljava/io/PrintStream;
         3: ldc           #13                 // String Hello World!
         5: invokevirtual #15                 // Method java/io/PrintStream.println:(Ljava/lang/String;)V
         8: return
      LineNumberTable:
        line 3: 0
        line 4: 8
}
SourceFile: "HelloWorld.java"
```
